agishell/__init__.py
agishell/__version__.py
agishell/aigc.py
agishell/utils.py
agishell/hardwares/__init__.py
agishell/hardwares/audio130x.py
agishell/llm/__init__.py
agishell/llm/llm.py
agishell/tools/__init__.py
agishell/tools/speech_to_text.py
agishell/tools/speex_decoder.py
agishell/tools/text_to_speech.py
agishell-1.0.5.dist-info/LICENSE
agishell-1.0.5.dist-info/METADATA
agishell-1.0.5.dist-info/WHEEL
agishell-1.0.5.dist-info/top_level.txt
agishell-1.0.5.dist-info/RECORD
