Metadata-Version: 2.1
Name: agishell
Version: 1.0.5
License-File: LICENSE
Requires-Dist: python-dotenv ==1.0.1
Requires-Dist: aiohttp ==3.9.3
Requires-Dist: reactivex ==4.0.4
Requires-Dist: tenacity ==8.2.3
Requires-Dist: tiktoken ==0.6.0
Requires-Dist: SpeechRecognition
Requires-Dist: loguru
Requires-Dist: requests
Requires-Dist: pyserial
Requires-Dist: openai
